{
  "trainingPhrases": [
    {
      "parts": [
        {
          "text": "hi"
        }
      ],
      "repeatCount": 1,
      "languageCode": "en"
    },
    {
      "parts": [
        {
          "text": "hello"
        }
      ],
      "repeatCount": 1,
      "languageCode": "en"
    },
    {
      "parts": [
        {
          "text": "hey"
        }
      ],
      "repeatCount": 1,
      "languageCode": "en"
    },
    {
      "parts": [
        {
          "text": "help me"
        }
      ],
      "repeatCount": 1,
      "languageCode": "en"
    },
    {
      "parts": [
        {
          "text": "get started"
        }
      ],
      "repeatCount": 1,
      "languageCode": "en"
    },
    {
      "parts": [
        {
          "text": "I'm interested in CivicAI"
        }
      ],
      "repeatCount": 1,
      "languageCode": "en"
    },
    {
      "parts": [
        {
          "text": "tell me about your product"
        }
      ],
      "repeatCount": 1,
      "languageCode": "en"
    },
    {
      "parts": [
        {
          "text": "I need help"
        }
      ],
      "repeatCount": 1,
      "languageCode": "en"
    },
    {
      "parts": [
        {
          "text": "hello there"
        }
      ],
      "repeatCount": 1,
      "languageCode": "en"
    },
    {
      "parts": [
        {
          "text": "good morning"
        }
      ],
      "repeatCount": 1,
      "languageCode": "en"
    },
    {
      "parts": [
        {
          "text": "good afternoon"
        }
      ],
      "repeatCount": 1,
      "languageCode": "en"
    },
    {
      "parts": [
        {
          "text": "I'm looking for information"
        }
      ],
      "repeatCount": 1,
      "languageCode": "en"
    },
    {
      "parts": [
        {
          "text": "can you help me"
        }
      ],
      "repeatCount": 1,
      "languageCode": "en"
    },
    {
      "parts": [
        {
          "text": "I'm interested"
        }
      ],
      "repeatCount": 1,
      "languageCode": "en"
    },
    {
      "parts": [
        {
          "text": "start"
        }
      ],
      "repeatCount": 1,
      "languageCode": "en"
    }
  ]
}
